CHANGES.rst
LICENSE
MANIFEST.in
README.rst
setup.py
ecreall_pontus.egg-info/PKG-INFO
ecreall_pontus.egg-info/SOURCES.txt
ecreall_pontus.egg-info/dependency_links.txt
ecreall_pontus.egg-info/entry_points.txt
ecreall_pontus.egg-info/not-zip-safe
ecreall_pontus.egg-info/requires.txt
ecreall_pontus.egg-info/top_level.txt
pontus/__init__.py
pontus/core.py
pontus/default_behavior.py
pontus/form.py
pontus/index.py
pontus/interfaces.py
pontus/layout.py
pontus/panels.py
pontus/schema.py
pontus/testing.py
pontus/util.py
pontus/view.py
pontus/view_operation.py
pontus/widget.py
pontus/file/__init__.py
pontus/file/view.py
pontus/file/templates/file_upload.pt
pontus/file/templates/img_upload.pt
pontus/locale/pontus.pot
pontus/locale/fr/LC_MESSAGES/pontus.mo
pontus/locale/fr/LC_MESSAGES/pontus.po
pontus/resources/__init__.py
pontus/static/cropper-master/.editorconfig
pontus/static/cropper-master/Gruntfile.js
pontus/static/cropper-master/LICENSE.md
pontus/static/cropper-master/README.md
pontus/static/cropper-master/bower.json
pontus/static/cropper-master/package.json
pontus/static/cropper-master/demos/index.html
pontus/static/cropper-master/demos/css/bootstrap.min.css
pontus/static/cropper-master/demos/css/docs.css
pontus/static/cropper-master/demos/img/picture-1.jpg
pontus/static/cropper-master/demos/img/picture-2.jpg
pontus/static/cropper-master/demos/js/bootstrap.min.js
pontus/static/cropper-master/demos/js/docs.js
pontus/static/cropper-master/demos/js/jquery.min.js
pontus/static/cropper-master/dist/cropper.css
pontus/static/cropper-master/dist/cropper.js
pontus/static/cropper-master/dist/cropper.min.css
pontus/static/cropper-master/dist/cropper.min.js
pontus/static/cropper-master/docs/index.html
pontus/static/cropper-master/docs/css/docs.css
pontus/static/cropper-master/docs/dist/cropper.css
pontus/static/cropper-master/docs/dist/cropper.js
pontus/static/cropper-master/docs/dist/cropper.min.css
pontus/static/cropper-master/docs/dist/cropper.min.js
pontus/static/cropper-master/docs/img/picture-1.jpg
pontus/static/cropper-master/docs/img/picture-2.jpg
pontus/static/cropper-master/docs/js/docs.js
pontus/static/cropper-master/examples/crop-avatar/README.md
pontus/static/cropper-master/examples/crop-avatar/crop-avatar.html
