Metadata-Version: 1.1
Name: ecreall-pontus
Version: 1.1.0
Summary: An application programming interface built upon the Pyramid web framework and substanced application. It provides libraries which make it easy to manage complex and imbricated views. For that purpose, Pontus introduces the concept of operations on views.
Home-page: https://github.com/ecreall/pontus/
Author: Amen Souissi
Author-email: amensouissi@ecreall.com
License: AGPLv3+
Keywords: process
Platform: UNKNOWN
Classifier: Programming Language :: Python
Classifier: Programming Language :: Python :: 3.4
Classifier: Framework :: Pyramid
Classifier: Topic :: Internet :: WWW/HTTP
Classifier: Topic :: Internet :: WWW/HTTP :: WSGI :: Application
Classifier: License :: OSI Approved :: GNU Affero General Public License v3 or later (AGPLv3+)
